funapi/__init__.py
funtext-0.0.1.dist-info/LICENSE
funtext-0.0.1.dist-info/METADATA
funtext-0.0.1.dist-info/WHEEL
funtext-0.0.1.dist-info/entry_points.txt
funtext-0.0.1.dist-info/top_level.txt
funtext-0.0.1.dist-info/RECORD
